vittoriadb/__init__.py
vittoriadb/client.py
vittoriadb/configure.py
vittoriadb/document.py
vittoriadb/types.py
vittoriadb-0.6.0.dist-info/METADATA
vittoriadb-0.6.0.dist-info/WHEEL
vittoriadb-0.6.0.dist-info/entry_points.txt
vittoriadb-0.6.0.dist-info/top_level.txt
vittoriadb-0.6.0.dist-info/RECORD
