Metadata-Version: 2.4
Name: vittoriadb
Version: 0.6.0
Summary: High-performance vector database with unified configuration, I/O optimization, and automatic embeddings
Home-page: https://github.com/antonellof/VittoriaDB
Author: VittoriaDB Team
Author-email: team@vittoriadb.dev
Project-URL: Source, https://github.com/antonellof/VittoriaDB
Project-URL: Tracker, https://github.com/antonellof/VittoriaDB/issues
Project-URL: Changelog, https://github.com/antonellof/VittoriaDB/releases
Project-URL: Examples, https://github.com/antonellof/VittoriaDB/tree/main/examples
Keywords: vector database,embeddings,similarity search,AI,machine learning,RAG,SIMD,parallel search,configuration,performance
Classifier: Development Status :: 4 - Beta
Classifier: Intended Audience :: Developers
Classifier: Topic :: Database
Classifier: Topic :: Scientific/Engineering :: Artificial Intelligence
Classifier: License :: OSI Approved :: MIT License
Classifier: Programming Language :: Python :: 3
Classifier: Programming Language :: Python :: 3.7
Classifier: Programming Language :: Python :: 3.8
Classifier: Programming Language :: Python :: 3.9
Classifier: Programming Language :: Python :: 3.10
Classifier: Programming Language :: Python :: 3.11
Classifier: Operating System :: OS Independent
Requires-Python: >=3.7
Requires-Dist: requests>=2.25.0
Provides-Extra: dev
Requires-Dist: pytest>=6.0; extra == "dev"
Requires-Dist: pytest-cov>=2.0; extra == "dev"
Requires-Dist: black>=21.0; extra == "dev"
Requires-Dist: mypy>=0.900; extra == "dev"
Requires-Dist: flake8>=3.8; extra == "dev"
Provides-Extra: full
Requires-Dist: sentence-transformers>=2.0; extra == "full"
Requires-Dist: transformers>=4.0; extra == "full"
Requires-Dist: torch>=1.9; extra == "full"
Requires-Dist: numpy>=1.20; extra == "full"
Provides-Extra: docs
Requires-Dist: sphinx>=4.0; extra == "docs"
Requires-Dist: sphinx-rtd-theme>=1.0; extra == "docs"
Requires-Dist: myst-parser>=0.15; extra == "docs"
Dynamic: author
Dynamic: author-email
Dynamic: classifier
Dynamic: description
Dynamic: description-content-type
Dynamic: home-page
Dynamic: keywords
Dynamic: project-url
Dynamic: provides-extra
Dynamic: requires-dist
Dynamic: requires-python
Dynamic: summary
